[
    {
        "name": "judit camps",
        "birthdate": "1999-11-27",
        "email": "judit@camps.com",
        "username": "juditcamps",
        "password": "123qwe123",
        "id": "91t0snn7z9c",
        "status": "online"
    },
    {
        "name": "eva camps",
        "birthdate": "2002-12-19",
        "email": "eva@camps.com",
        "username": "evacamps",
        "password": "123qwe123",
        "id": "3vikhp04fz2",
        "status": "offline"
    },
    {
        "name": "mar galobart",
        "birthdate": "1999-08-12",
        "email": "mar@galobart.com",
        "username": "margalobart",
        "password": "123qwe123",
        "id": "h4xnop3ics8"
    },
    {
        "name": "luca reichert",
        "birthdate": "1999-03-11",
        "email": "luca@reichert.com",
        "username": "lucareichert",
        "password": "123qwe123",
        "id": "n1s7wfht3gw",
        "status": "online"
    }
]